cloakensdk/__init__.py
cloakensdk/client.py
cloakensdk/resources.py
cloakensdk/utility.py
cloakensdk-0.0.8.dist-info/LICENSE
cloakensdk-0.0.8.dist-info/METADATA
cloakensdk-0.0.8.dist-info/WHEEL
cloakensdk-0.0.8.dist-info/top_level.txt
cloakensdk-0.0.8.dist-info/RECORD
