Metadata-Version: 2.1
Name: cloakensdk
Version: 0.0.8
Summary: SDK for use with Cloaken url unshortener AMI
Home-page: https://gitlab.com/guzzijob/cloakensdk
Author: Aaron Jonen
Author-email: ajonen@mailcan.com
License: UNKNOWN
Platform: UNKNOWN
Classifier: Programming Language :: Python :: 3
Classifier: License :: OSI Approved :: MIT License
Classifier: Operating System :: OS Independent
Requires-Dist: requests
Requires-Dist: requests-futures
Requires-Dist: urllib3
